kandc/__init__.py
kandc/constants.py
kandc/annotators/__init__.py
kandc/annotators/profiler.py
kandc/annotators/timing.py
kandc/annotators/trace.py
kandc/api/__init__.py
kandc/api/auth.py
kandc/api/client.py
kandc/cli/__init__.py
kandc/cli/main.py
kandc/core/__init__.py
kandc/core/run.py
kandc/core/snapshot.py
kandc-0.0.29.dist-info/licenses/LICENSE
kandc-0.0.29.dist-info/METADATA
kandc-0.0.29.dist-info/WHEEL
kandc-0.0.29.dist-info/entry_points.txt
kandc-0.0.29.dist-info/top_level.txt
kandc-0.0.29.dist-info/RECORD
